{"vendors":[{"id":5,"name":"Amazon","vendor_link":"http:\/\/www.amazon.com\/","vendor_logo":"\/public\/images\/vendor_badges\/AmazonButtonTrans.png","vendor_search_url":"http:\/\/www.amazon.com\/s\/ref=nb_sb_noss?url=search-alias%3Dmovies-tv&field-keywords="},{"id":6,"name":"Crackle","vendor_link":"http:\/\/www.crackle.com\/","vendor_logo":"\/public\/images\/vendor_badges\/crackle.jpg","vendor_search_url":null},{"id":2,"name":"Google Play","vendor_link":"https:\/\/play.google.com\/store","vendor_logo":"\/public\/images\/vendor_badges\/google_play.png","vendor_search_url":"https:\/\/play.google.com\/store\/search?c=movies&q="},{"id":12,"name":"History Channel","vendor_link":"http:\/\/www.history.com","vendor_logo":"\/public\/images\/vendor_badges\/HistoryButtonTrans.png","vendor_search_url":"http:\/\/www.history.com\/search?q="},{"id":4,"name":"Hulu Plus","vendor_link":"http:\/\/www.hulu.com\/plus","vendor_logo":"\/public\/images\/vendor_badges\/hulu_plus.png","vendor_search_url":null},{"id":1,"name":"iTunes","vendor_link":"https:\/\/www.apple.com\/itunes\/","vendor_logo":"\/public\/images\/vendor_badges\/itunes.png","vendor_search_url":null},{"id":11,"name":"National Geographic","vendor_link":"http:\/\/www.nationalgeographic.com\/","vendor_logo":"\/public\/images\/vendor_badges\/NationalGeographicButtonTrans.png","vendor_search_url":"http:\/\/www.nationalgeographic.com\/search?q="},{"id":3,"name":"NetFlix","vendor_link":"http:\/\/www.netflix.com\/","vendor_logo":"\/public\/images\/vendor_badges\/NetflixButtonTrans.png","vendor_search_url":"http:\/\/www.netflix.com\/search\/"},{"id":100,"name":"other","vendor_link":null,"vendor_logo":"\/public\/images\/vendor_badges\/LinkButtonTrans.png","vendor_search_url":null},{"id":9,"name":"PBS","vendor_link":"http:\/\/www.pbs.org\/","vendor_logo":"\/public\/images\/vendor_badges\/PBSButtonTrans.png","vendor_search_url":null},{"id":10,"name":"PBS Kids","vendor_link":"http:\/\/pbskids.org\/","vendor_logo":"\/public\/images\/vendor_badges\/PBSButtonTrans.png","vendor_search_url":null},{"id":7,"name":"RedBox Instant","vendor_link":"http:\/\/www.redboxinstant.com\/","vendor_logo":"\/public\/images\/vendor_badges\/redbox_instant.jpg","vendor_search_url":null},{"id":13,"name":"Ted Ed TV","vendor_link":"http:\/\/ed.ted.com\/","vendor_logo":"\/public\/images\/vendor_badges\/LinkButtonTrans.png","vendor_search_url":null},{"id":8,"name":"YouTube","vendor_link":"https:\/\/www.youtube.com\/","vendor_logo":"\/public\/images\/vendor_badges\/YouTubeButtonTrans.png","vendor_search_url":"https:\/\/www.youtube.com\/results?search_query="}]}